LICENSE
MANIFEST.in
README.rst
setup.cfg
setup.py
gapic_google_iam_admin_v1.egg-info/PKG-INFO
gapic_google_iam_admin_v1.egg-info/SOURCES.txt
gapic_google_iam_admin_v1.egg-info/dependency_links.txt
gapic_google_iam_admin_v1.egg-info/namespace_packages.txt
gapic_google_iam_admin_v1.egg-info/requires.txt
gapic_google_iam_admin_v1.egg-info/top_level.txt
google/__init__.py
google/__init__.pyc
google/cloud/__init__.py
google/cloud/gapic/__init__.py
google/cloud/gapic/iam_admin/__init__.py
google/cloud/gapic/iam_admin/v1/__init__.py
google/cloud/gapic/iam_admin/v1/enums.py
google/cloud/gapic/iam_admin/v1/iam_api.py
google/cloud/gapic/iam_admin/v1/iam_client_config.json